README.md
setup.py
marckraw_hello_world/__init__.py
marckraw_hello_world/sample.py
marckraw_hello_world.egg-info/PKG-INFO
marckraw_hello_world.egg-info/SOURCES.txt
marckraw_hello_world.egg-info/dependency_links.txt
marckraw_hello_world.egg-info/top_level.txt