Metadata-Version: 2.1
Name: marckraw-hello-world
Version: 1.0.8
Summary: Sample PYPI App
Home-page: UNKNOWN
License: UNKNOWN
Platform: UNKNOWN
